easybash/__init__.py
easybash/basher.py
easybash-1.0.0.dist-info/LICENSE
easybash-1.0.0.dist-info/METADATA
easybash-1.0.0.dist-info/WHEEL
easybash-1.0.0.dist-info/top_level.txt
easybash-1.0.0.dist-info/RECORD
