Metadata-Version: 2.1
Name: easybash
Version: 1.0.0
Summary: A Python shell command helper using the subprocess Popen.
Author: André Luís
Author-email: andreluisos@me.com
License: GPLv3
Project-URL: Source, https://github.com/andreluisos/easybash
Project-URL: Documentation, https://github.com/andreluisos/easybash
Project-URL: Issues, https://github.com/andreluisos/easybash/issues
Keywords: bash,sh,shell,linux
Classifier: License :: OSI Approved :: GNU General Public License v3 (GPLv3)
Classifier: Operating System :: POSIX :: Linux
Classifier: Programming Language :: Python :: 3
License-File: LICENSE
